{"disbursementEvent":null,"repaymentEvent":null,"systemEvent":{"id":592,"loanId":3293,"eventType":"PRFEDECO","date":"2019-04-16","createdOn":"2019-04-16T10:27:15.310","createdBy":"operator","lastModifiedOn":"2019-04-16T10:27:15.310","lastModifiedBy":"operator"},"interestAccrualEvent":null,"demandList":[{"id":1316,"loanId":3293,"eventType":"PRFEDECO","eventId":592,"demandType":"FEE","feeId":471,"demandDate":"2019-04-07","calculatedAmount":100.000000,"dueAmount":100.000000,"demandCurrency":"USD","remarks":"null inserted through batch job","reversed":null,"createdOn":"2019-04-16T10:27:15.32Z","createdBy":"operator","lastModifiedOn":"2019-04-16T10:27:15.32Z","lastModifiedBy":"operator","deleted":false},{"id":1317,"loanId":3293,"eventType":"PRFEDECO","eventId":592,"demandType":"FEE","feeId":471,"demandDate":"2019-04-07","calculatedAmount":100.000000,"dueAmount":100.000000,"demandCurrency":"USD","remarks":"null inserted through batch job","reversed":null,"createdOn":"2019-04-16T10:27:15.361Z","createdBy":"operator","lastModifiedOn":"2019-04-16T10:27:15.361Z","lastModifiedBy":"operator","deleted":false}],"collection":null,"demandCollectionList":null,"payoutList":[],"loanTransaction":{"id":5557,"loanId":3293,"eventType":"PRFEDECO","eventId":592,"transactionDate":"2019-04-07","transactionAmount":100.000000,"transactionCurrency":"USD","reversalEventType":null,"reversalEventId":null,"reversalEventDate":null,"reverseTransactionRef":null,"createdOn":"2019-04-16T10:27:15.362Z","createdBy":"operator","lastModifiedOn":"2019-04-16T10:27:15.362Z","lastModifiedBy":"operator","reversible":false,"reversed":false},"loanBalances":{"retainedInterestAdvance":0.000000,"retainedInterestUtilized":0.000000,"cashCollateralAdvance":0.000000,"cashCollateralUtilized":0.000000,"excessPayAdvance":0.000000,"excessPayUtilized":0.000000,"disbursedPrincipal":10000000.000000,"lastDisbursedDate":"2019-03-06","totalPrincipalPaid":0.000000,"totalInterestPaid":0.000000,"totalFeePaid":0.000000,"totalPenaltyPaid":0.000000,"totalPaid":0.000000,"principalBalance":10000000.000000,"feeBalance":0.000000,"penaltyBalance":0.000000,"accruedPenalty":0.000000,"accruedInterest":0.000000,"accruedInterestBooked":0.00,"accruedUptoRuntime":null,"accruedUpto":null,"lastInterestAppliedDate":null,"interestFromArrearsAccrued":0.000000,"interestFromArrearsPaid":0.000000,"interestFromArrearsBalance":0.000000,"retainedInterestId":null,"cashCollateralId":null},"journalEntry":{"entityId":"odin3831auris3","entityName":"portfolio","entityEvent":"PRFEDECO","currency":"USD","transactionIdentifier":"5557","transactionDate":"2019-04-16T10:27:15.362Z","transactionType":"PRFEDECO","isSystemInitiated":null,"clerk":"operator","note":"Periodic Fee Records","debtors":[{"sequenceNo":null,"accountNumber":"1USDASSET","amount":"100.0","description":null}],"creditors":[{"sequenceNo":null,"accountNumber":"1USDREVENUE","amount":"100.0","description":null}],"state":"PROCESSED","message":"Periodic Fee"}}
