{"data":null,"errorResponse":{"timestamp":"2019-03-03T11:59:43.883","status":"400","error":"Bad Request","errorMessage":"Business Logic Error","exception":"org.apache.fineract.cn.lang.BusinessLogicException","errors":[{"codes":["400"],"arguments":["From date should be after previous slab date"],"defaultMessage":"From date should be after previous slab date"},{"codes":["400"],"arguments":["Fee percentage value can not be null for %cent of linked amount fee formula"],"defaultMessage":"Fee percentage value can not be null for %cent of linked amount fee formula"}],"path":"/loanaccount"}}
